flow360client/IOutils.py
flow360client/__init__.py
flow360client/authentication.py
flow360client/case.py
flow360client/casehelper.py
flow360client/config.py
flow360client/errorHandling.py
flow360client/fun3d_to_flow360.py
flow360client/httputils.py
flow360client/mesh.py
flow360client/meshUtils.py
flow360client/s3utils.py
flow360client/studio.py
flow360client/surfaceMesh.py
flow360client/task.py
flow360client/validation.py
flow360client/version.py
flow360client/versionCheck.py
flow360client/generator/__init__.py
flow360client/generator/case.py
flow360client/generator/caseBoundary.py
flow360client/generator/caseFreestream.py
flow360client/generator/caseGeometry.py
flow360client/generator/caseNavierStokesSolver.py
flow360client/generator/caseOutput.py
flow360client/generator/caseSlidingInterfaces.py
flow360client/generator/caseTimeStepping.py
flow360client/generator/caseTurbulenceSolver.py
flow360client/generator/core.py
flow360client/generator/meshInfo.py
flow360client-23.3.2.2.dist-info/METADATA
flow360client-23.3.2.2.dist-info/WHEEL
flow360client-23.3.2.2.dist-info/dependency_links.txt
flow360client-23.3.2.2.dist-info/top_level.txt
flow360client-23.3.2.2.dist-info/RECORD
